loadingutils/__init__.py
loadingutils/main.py
loadingutils-0.1.0.dist-info/licenses/LICENSE
loadingutils-0.1.0.dist-info/METADATA
loadingutils-0.1.0.dist-info/WHEEL
loadingutils-0.1.0.dist-info/top_level.txt
loadingutils-0.1.0.dist-info/RECORD
