Metadata-Version: 2.4
Name: loadingutils
Version: 0.1.0
Summary: Simple console loaders and spinners
Author-email: "Koen V." <koenesmiley@gmail.com>
License: MIT
Project-URL: Homepage, https://github.com/Koen-mods/pyloading
Requires-Python: >=3.8
License-File: LICENSE
Dynamic: license-file
